__init__.py
circumcenter.py
coordinate.py
2dutils-1.2.0.dist-info/LICENSE
2dutils-1.2.0.dist-info/METADATA
2dutils-1.2.0.dist-info/WHEEL
2dutils-1.2.0.dist-info/top_level.txt
2dutils-1.2.0.dist-info/RECORD
