Metadata-Version: 2.1
Name: 2dutils
Version: 1.2.0
Summary: A collection of 2D utilities for coordinate representation and manipulation.
Author-email: Paulo Sanchez <dev.szblzpaulo@gmail.com>
Project-URL: Homepage, https://github.com/erlete/2dutils
Project-URL: Bug Tracker, https://github.com/erlete/2dutils/issues
Classifier: Intended Audience :: Developers
Classifier: Programming Language :: Python :: 3
Classifier: License :: OSI Approved :: GNU General Public License v3 (GPLv3)
Classifier: Operating System :: OS Independent
Requires-Python: >=3.10
License-File: LICENSE
